{"asset": {                "version": "0.0",                "gltfUpAxis": "Y"            },            "geometricError":100.000000,"root": {                "transform": [-0.969578,-0.244781,0.000000,0.000000,0.124074,-0.491458,0.862018,0.000000,-0.210640,0.834346,0.509409,0.000000,-1344658.551228,5326200.226911,3230138.939659,1],                "boundingVolume": {                    "region": [1.818009,0.534433,1.818171,0.534564,0.000000,48.000000]},"geometricError": 100.000000,                        "refine": "REPLACE",                        "content": {                            "uri": "./tile/5/27/8.b3dm"}}}