{"asset": {                "version": "0.0",                "gltfUpAxis": "Y"            },            "geometricError":100.000000,"root": {                "transform": [-0.970415,-0.241444,0.000000,0.000000,0.122483,-0.492284,0.861774,0.000000,-0.207709,0.834827,0.509825,0.000000,-1325952.094729,5329276.666739,3232778.883612,1],                "boundingVolume": {                    "region": [1.814554,0.534909,1.814747,0.535054,0.000000,36.000000]},"geometricError": 100.000000,                        "refine": "REPLACE",                        "content": {                            "uri": "./tile/5/4/12.b3dm"}}}