{"asset": {                "version": "0.0",                "gltfUpAxis": "Y"            },            "geometricError":100.000000,"root": {                "transform": [-0.969798,-0.243908,0.000000,0.000000,0.123981,-0.492961,0.861173,0.000000,-0.209681,0.833709,0.510846,0.000000,-1338540.941777,5322158.589094,3239267.070545,1],                "boundingVolume": {                    "region": [1.817112,0.536105,1.817267,0.536233,0.000000,36.000000]},"geometricError": 100.000000,                        "refine": "REPLACE",                        "content": {                            "uri": "./tile/5/21/22.b3dm"}}}