{"asset": {                "version": "0.0",                "gltfUpAxis": "Y"            },            "geometricError":100.000000,"root": {                "transform": [-0.970162,-0.242456,0.000000,0.000000,0.122994,-0.492149,0.861778,0.000000,-0.208581,0.834614,0.509818,0.000000,-1331514.095011,5327916.565259,3232734.950668,1],                "boundingVolume": {                    "region": [1.815616,0.534909,1.815769,0.535038,0.000000,46.000000]},"geometricError": 100.000000,                        "refine": "REPLACE",                        "content": {                            "uri": "./tile/5/11/12.b3dm"}}}