{"asset": {                "version": "0.0",                "gltfUpAxis": "Y"            },            "geometricError":100.000000,"root": {                "transform": [-0.970197,-0.242318,0.000000,0.000000,0.123026,-0.492572,0.861532,0.000000,-0.208402,0.834403,0.510236,0.000000,-1330376.480244,5326577.616524,3235390.782580,1],                "boundingVolume": {                    "region": [1.815463,0.535386,1.815639,0.535533,0.000000,69.000000]},"geometricError": 100.000000,                        "refine": "REPLACE",                        "content": {                            "uri": "./tile/5/10/16.b3dm"}}}