{"asset": {                "version": "0.0",                "gltfUpAxis": "Y"            },            "geometricError":100.000000,"root": {                "transform": [-0.970199,-0.242309,0.000000,0.000000,0.123069,-0.492767,0.861414,0.000000,-0.208365,0.834289,0.510436,0.000000,-1330142.745931,5325858.319812,3236662.196733,1],                "boundingVolume": {                    "region": [1.815452,0.535625,1.815631,0.535759,0.000000,122.000000]},"geometricError": 100.000000,                        "refine": "REPLACE",                        "content": {                            "uri": "./tile/5/10/18.b3dm"}}}