{"asset": {                "version": "0.0",                "gltfUpAxis": "Y"            },            "geometricError":100.000000,"root": {                "transform": [-0.969617,-0.244627,0.000000,0.000000,0.123845,-0.490880,0.862380,0.000000,-0.210597,0.834733,0.508792,0.000000,-1344381.394783,5328661.948974,3226218.241951,1],                "boundingVolume": {                    "region": [1.817841,0.533715,1.818022,0.533847,0.000000,36.000000]},"geometricError": 100.000000,                        "refine": "REPLACE",                        "content": {                            "uri": "./tile/5/26/2.b3dm"}}}