{"asset": {                "version": "0.0",                "gltfUpAxis": "Y"            },            "geometricError":100.000000,"root": {                "transform": [-0.970383,-0.241573,0.000000,0.000000,0.122523,-0.492166,0.861835,0.000000,-0.207835,0.834859,0.509720,0.000000,-1326756.248705,5329482.722942,3232113.674381,1],                "boundingVolume": {                    "region": [1.814695,0.534790,1.814872,0.534929,0.000000,72.000000]},"geometricError": 100.000000,                        "refine": "REPLACE",                        "content": {                            "uri": "./tile/5/5/11.b3dm"}}}