{"asset": {                "version": "0.0",                "gltfUpAxis": "Y"            },            "geometricError":100.000000,"root": {                "transform": [-0.969909,-0.243470,0.000000,0.000000,0.123658,-0.492617,0.861416,0.000000,-0.209364,0.834041,0.510434,0.000000,-1336515.620055,5324271.053778,3236648.434212,1],                "boundingVolume": {                    "region": [1.816651,0.535625,1.816824,0.535754,0.000000,72.000000]},"geometricError": 100.000000,                        "refine": "REPLACE",                        "content": {                            "uri": "./tile/5/18/18.b3dm"}}}